packmol_step/__init__.py
packmol_step/__main__.py
packmol_step/_version.py
packmol_step/installer.py
packmol_step/packmol.py
packmol_step/packmol_parameters.py
packmol_step/packmol_step.py
packmol_step/tk_packmol.py
packmol_step/data/configuration.txt
packmol_step/data/packmol.ini
packmol_step/data/references.bib
packmol_step/data/seamm-packmol.yml
packmol_step-2026.1.7.dist-info/licenses/AUTHORS.rst
packmol_step-2026.1.7.dist-info/licenses/LICENSE
packmol_step-2026.1.7.dist-info/METADATA
packmol_step-2026.1.7.dist-info/WHEEL
packmol_step-2026.1.7.dist-info/entry_points.txt
packmol_step-2026.1.7.dist-info/top_level.txt
packmol_step-2026.1.7.dist-info/zip-safe
packmol_step-2026.1.7.dist-info/RECORD
